{
  "project_info": {
    "project_number": "621763371413",
    "project_id": "blnproject-690c2",
    "storage_bucket": "blnproject-690c2.appspot.com"
  },
  "client": [
    {
      "client_info": {
        "mobilesdk_app_id": "1:621763371413:android:699435c1fa7705642f169c",
        "android_client_info": {
          "package_name": "com.bln.app"
        }
      },
      "oauth_client": [],
      "api_key": [
        {
          "current_key": "AIzaSyAwG-LiM0qc0QvD08jIm6Pxjjsbk-wtEDY"
        }
      ],
      "services": {
        "appinvite_service": {
          "other_platform_oauth_client": []
        }
      }
    },
    {
      "client_info": {
        "mobilesdk_app_id": "1:621763371413:android:61dd94500e5d17c52f169c",
        "android_client_info": {
          "package_name": "com.example.bln_admin"
        }
      },
      "oauth_client": [],
      "api_key": [
        {
          "current_key": "AIzaSyAwG-LiM0qc0QvD08jIm6Pxjjsbk-wtEDY"
        }
      ],
      "services": {
        "appinvite_service": {
          "other_platform_oauth_client": []
        }
      }
    },
    {
      "client_info": {
        "mobilesdk_app_id": "1:621763371413:android:99e25558095a1ec42f169c",
        "android_client_info": {
          "package_name": "com.example.bln_website"
        }
      },
      "oauth_client": [],
      "api_key": [
        {
          "current_key": "AIzaSyAwG-LiM0qc0QvD08jIm6Pxjjsbk-wtEDY"
        }
      ],
      "services": {
        "appinvite_service": {
          "other_platform_oauth_client": []
        }
      }
    }
  ],
  "configuration_version": "1"
}